libmgrs.cpython-312-aarch64-linux-musl.so
libmgrs/mgrs.c
libmgrs/mgrs.h
libmgrs/polarst.c
libmgrs/polarst.h
libmgrs/tranmerc.c
libmgrs/tranmerc.h
libmgrs/ups.c
libmgrs/ups.h
libmgrs/utm.c
libmgrs/utm.h
mgrs/__init__.py
mgrs/core.py
mgrs-1.5.3.dist-info/METADATA
mgrs-1.5.3.dist-info/WHEEL
mgrs-1.5.3.dist-info/top_level.txt
mgrs-1.5.3.dist-info/RECORD
mgrs-1.5.3.dist-info/licenses/LICENSE
