Metadata-Version: 2.4
Name: mgrs
Version: 1.5.3
Summary: MGRS coordinate conversion for Python
Author: Howard Butler
Author-email: howard@hobu.co
Maintainer-email: Howard Butler <howard@hobu.co>
License: The MIT License (MIT)
Project-URL: repository, https://github.com/hobuinc/mgrs/
Project-URL: changelog, https://github.com/hobuinc/mgrs/commits/main/
Keywords: gis,coordinate,conversion
Classifier: Development Status :: 5 - Production/Stable
Classifier: Intended Audience :: Developers
Classifier: Intended Audience :: Science/Research
Classifier: License :: OSI Approved :: BSD License
Classifier: Operating System :: OS Independent
Classifier: Programming Language :: Python :: 3.9
Classifier: Programming Language :: Python :: 3.10
Classifier: Programming Language :: Python :: 3.11
Classifier: Programming Language :: Python :: 3.12
Classifier: Topic :: Scientific/Engineering :: GIS
Requires-Python: >=3.9
License-File: LICENSE
Dynamic: license-file
